[
  {
    "id": "act-3e-diviseurs",
    "grade": "3e",
    "title": "Liste des diviseurs et nombres premiers",
    "emoji": "🔢",
    "pdfUrl": "https://drive.google.com/file/d/1L5GTLZpzTNGDGZtpvPOki99wdZtGAh5M/view?usp=drive_link",
    "pdfName": "Consignes.pdf",
    "pdfEmbedUrl": "https://drive.google.com/file/d/1L5GTLZpzTNGDGZtpvPOki99wdZtGAh5M/preview",
    "pdfDownloadUrl": "https://drive.google.com/uc?id=1L5GTLZpzTNGDGZtpvPOki99wdZtGAh5M&export=download",
    "scratchId": "339277505",
    "scratchIds": [
      "339277505"
    ],
    "active": true,
    "createdAt": "2026-01-01T08:00:00.000Z",
    "updatedAt": "2026-07-21T14:26:05.079Z"
  },
  {
    "id": "act-3e-images",
    "grade": "3e",
    "title": "Images et antécédents",
    "emoji": "💻",
    "pdfUrl": "https://drive.google.com/file/d/11eWwxX4JbuoF-OqJ9WNAmdSK8YSeW4ul/view?usp=drive_link",
    "pdfName": "Consignes.pdf",
    "pdfEmbedUrl": "https://drive.google.com/file/d/11eWwxX4JbuoF-OqJ9WNAmdSK8YSeW4ul/preview",
    "pdfDownloadUrl": "https://drive.google.com/uc?id=11eWwxX4JbuoF-OqJ9WNAmdSK8YSeW4ul&export=download",
    "scratchId": "282542420",
    "scratchIds": [
      "282542420"
    ],
    "active": true,
    "createdAt": "2026-01-01T08:01:00.000Z",
    "updatedAt": "2026-07-22T05:52:05.479Z"
  },
  {
    "id": "act-3e-temperatures",
    "grade": "3e",
    "title": "Conversions de températures",
    "emoji": "🌡️",
    "pdfUrl": "https://drive.google.com/file/d/1sg9O1hhHYuu_OyMcL3_kKGzDJZjacMwH/view?usp=drive_link",
    "pdfName": "Consignes.pdf",
    "pdfEmbedUrl": "https://drive.google.com/file/d/1sg9O1hhHYuu_OyMcL3_kKGzDJZjacMwH/preview",
    "pdfDownloadUrl": "https://drive.google.com/uc?id=1sg9O1hhHYuu_OyMcL3_kKGzDJZjacMwH&export=download",
    "scratchId": "144122707",
    "scratchIds": [
      "144122707"
    ],
    "active": true,
    "createdAt": "2026-01-01T08:02:00.000Z",
    "updatedAt": "2026-07-22T06:02:37.844Z"
  },
  {
    "id": "act-3e-moyennes",
    "grade": "3e",
    "title": "Moyennes et Médianes",
    "emoji": "📈",
    "pdfUrl": "https://drive.google.com/open?id=1O4moJe_bzBScq-ctHUf-7p7YxjpyK1SG",
    "pdfName": "Moyenne et médiane.pdf",
    "pdfEmbedUrl": "https://drive.google.com/file/d/1O4moJe_bzBScq-ctHUf-7p7YxjpyK1SG/preview",
    "pdfDownloadUrl": "https://drive.google.com/uc?id=1O4moJe_bzBScq-ctHUf-7p7YxjpyK1SG&export=download",
    "scratchId": "522457753",
    "scratchIds": [
      "522457753",
      "311035974"
    ],
    "active": true,
    "createdAt": "2026-01-01T08:03:00.000Z",
    "updatedAt": "2026-01-01T08:03:00.000Z"
  },
  {
    "id": "act-4e-pythagore",
    "grade": "4e",
    "title": "La réciproque de Pythagore",
    "emoji": "📐",
    "pdfUrl": "https://drive.google.com/open?id=12RiKSMBQDK7RhGNgHucfMsUmDGckEUqc",
    "pdfName": "Réciproque de Pythagore.pdf",
    "pdfEmbedUrl": "https://drive.google.com/file/d/12RiKSMBQDK7RhGNgHucfMsUmDGckEUqc/preview",
    "pdfDownloadUrl": "https://drive.google.com/uc?id=12RiKSMBQDK7RhGNgHucfMsUmDGckEUqc&export=download",
    "scratchId": "287154397",
    "scratchIds": [
      "287154397"
    ],
    "active": true,
    "createdAt": "2026-01-01T09:00:00.000Z",
    "updatedAt": "2026-01-01T09:00:00.000Z"
  },
  {
    "id": "act-4e-angles",
    "grade": "4e",
    "title": "Conversion des £ en €",
    "emoji": "🔄",
    "pdfUrl": "https://drive.google.com/open?id=1yY0nyouvS2E2AO8nWTuZUwspnD7Ov7jM",
    "pdfName": "Convertisseur £ en €.pdf",
    "pdfEmbedUrl": "https://drive.google.com/file/d/1yY0nyouvS2E2AO8nWTuZUwspnD7Ov7jM/preview",
    "pdfDownloadUrl": "https://drive.google.com/uc?id=1yY0nyouvS2E2AO8nWTuZUwspnD7Ov7jM&export=download",
    "scratchId": "173898198",
    "scratchIds": [
      "173898198"
    ],
    "active": true,
    "createdAt": "2026-01-01T09:01:00.000Z",
    "updatedAt": "2026-01-01T09:01:00.000Z"
  },
  {
    "id": "act-4e-moyenne",
    "grade": "4e",
    "title": "Calcul de moyenne et médiane",
    "emoji": "📊",
    "pdfUrl": "https://drive.google.com/open?id=1FJaegfP5gEymdV1MU2oIyXbtzttzqoMa",
    "pdfName": "Moyenne et médiane.pdf",
    "pdfEmbedUrl": "https://drive.google.com/file/d/1FJaegfP5gEymdV1MU2oIyXbtzttzqoMa/preview",
    "pdfDownloadUrl": "https://drive.google.com/uc?id=1FJaegfP5gEymdV1MU2oIyXbtzttzqoMa&export=download",
    "scratchId": "522457753",
    "scratchIds": [
      "522457753",
      "311035974"
    ],
    "active": false,
    "createdAt": "2026-01-01T09:02:00.000Z",
    "updatedAt": "2026-07-22T06:06:12.256Z"
  },
  {
    "id": "act-4e-litteral",
    "grade": "4e",
    "title": "Calcul Littéral",
    "emoji": "🔤",
    "pdfUrl": "https://drive.google.com/open?id=1SRE3iE3TKG5JVEDsmw8LUxrwYkv-PxQp",
    "pdfName": "Calcul littéral.pdf",
    "pdfEmbedUrl": "https://drive.google.com/file/d/1SRE3iE3TKG5JVEDsmw8LUxrwYkv-PxQp/preview",
    "pdfDownloadUrl": "https://drive.google.com/uc?id=1SRE3iE3TKG5JVEDsmw8LUxrwYkv-PxQp&export=download",
    "scratchId": "1161202414",
    "scratchIds": [
      "1161202414"
    ],
    "active": true,
    "createdAt": "2026-01-01T09:03:00.000Z",
    "updatedAt": "2026-01-01T09:03:00.000Z"
  },
  {
    "id": "act-5e-priorites",
    "grade": "5e",
    "title": "Priorités dans les calculs",
    "emoji": "🔢",
    "pdfUrl": "https://drive.google.com/open?id=1MY_1qajyD8NjDZ5ANxcDbcj3x24JP4TC",
    "pdfName": "Priorités dans les calculs V1.pdf",
    "pdfEmbedUrl": "https://drive.google.com/file/d/1MY_1qajyD8NjDZ5ANxcDbcj3x24JP4TC/preview",
    "pdfDownloadUrl": "https://drive.google.com/uc?id=1MY_1qajyD8NjDZ5ANxcDbcj3x24JP4TC&export=download",
    "scratchId": "1074074100",
    "scratchIds": [
      "1074074100"
    ],
    "active": true,
    "createdAt": "2026-01-01T10:00:00.000Z",
    "updatedAt": "2026-01-01T10:00:00.000Z"
  },
  {
    "id": "act-5e-fractions",
    "grade": "5e",
    "title": "Fractions incomplètes",
    "emoji": "➗",
    "pdfUrl": "https://drive.google.com/open?id=10mRIAuZW5t8O-s6lZGd1fAlorUfdyKqk",
    "pdfName": "Fraction incomplète.pdf",
    "pdfEmbedUrl": "https://drive.google.com/file/d/10mRIAuZW5t8O-s6lZGd1fAlorUfdyKqk/preview",
    "pdfDownloadUrl": "https://drive.google.com/uc?id=10mRIAuZW5t8O-s6lZGd1fAlorUfdyKqk&export=download",
    "scratchId": "1331680541",
    "scratchIds": [
      "1331680541"
    ],
    "active": true,
    "createdAt": "2026-01-01T10:01:00.000Z",
    "updatedAt": "2026-01-01T10:01:00.000Z"
  },
  {
    "id": "act-5e-relatifs",
    "grade": "5e",
    "title": "Calculs sur les nombres relatifs",
    "emoji": "➕",
    "pdfUrl": "https://drive.google.com/open?id=13aKK2aeudhJlOH4OkN_dfBe6Zyt8vQjX",
    "pdfName": "Calcul sur les relatifs.pdf",
    "pdfEmbedUrl": "https://drive.google.com/file/d/13aKK2aeudhJlOH4OkN_dfBe6Zyt8vQjX/preview",
    "pdfDownloadUrl": "https://drive.google.com/uc?id=13aKK2aeudhJlOH4OkN_dfBe6Zyt8vQjX&export=download",
    "scratchId": "174741757",
    "scratchIds": [
      "174741757"
    ],
    "active": true,
    "createdAt": "2026-01-01T10:02:00.000Z",
    "updatedAt": "2026-01-01T10:02:00.000Z"
  },
  {
    "id": "act-5e-chocolat",
    "grade": "5e",
    "title": "Le gâteau au chocolat",
    "emoji": "🍫",
    "pdfUrl": "https://drive.google.com/open?id=1hgrcQ95rFOWUTXhSw471P0HapvEohQfj",
    "pdfName": "Recette de gateau au chocolat.pdf",
    "pdfEmbedUrl": "https://drive.google.com/file/d/1hgrcQ95rFOWUTXhSw471P0HapvEohQfj/preview",
    "pdfDownloadUrl": "https://drive.google.com/uc?id=1hgrcQ95rFOWUTXhSw471P0HapvEohQfj&export=download",
    "scratchId": "166528869",
    "scratchIds": [
      "166528869"
    ],
    "active": true,
    "createdAt": "2026-01-01T10:03:00.000Z",
    "updatedAt": "2026-01-01T10:03:00.000Z"
  }
]
